PyHeap/Heap.py
PyHeap/HeapBase.py
PyHeap/__init__.py
PyHeap-0.0.4.dist-info/LICENSE
PyHeap-0.0.4.dist-info/METADATA
PyHeap-0.0.4.dist-info/WHEEL
PyHeap-0.0.4.dist-info/top_level.txt
PyHeap-0.0.4.dist-info/RECORD
