Metadata-Version: 2.1
Name: PyHeap
Version: 0.0.4
Summary: A small heap implementation with customizeable key
Home-page: https://github.com/Sammyalhashe/PyHeap
Author: Sammyalhashe
Author-email: sammy.alhashemi@mail.utoronto.ca
License: UNKNOWN
Platform: UNKNOWN
Classifier: Programming Language :: Python :: 3
Classifier: License :: OSI Approved :: MIT License
Classifier: Operating System :: OS Independent
Requires-Python: >=3.6
